debian/__init__.py
debian/_arch_table.py
debian/_util.py
debian/_version.py
debian/arfile.py
debian/changelog.py
debian/copyright.py
debian/deb822.py
debian/debfile.py
debian/debian_support.py
debian/debtags.py
debian/doc-debtags
debian/py.typed
debian/substvars.py
debian/watch.py
debian/_deb822_repro/__init__.py
debian/_deb822_repro/_util.py
debian/_deb822_repro/formatter.py
debian/_deb822_repro/locatable.py
debian/_deb822_repro/parsing.py
debian/_deb822_repro/tokens.py
debian/_deb822_repro/types.py
python_debian-1.0.1.dist-info/METADATA
python_debian-1.0.1.dist-info/WHEEL
python_debian-1.0.1.dist-info/top_level.txt
python_debian-1.0.1.dist-info/RECORD
