Metadata-Version: 2.1
Name: python-debian
Version: 1.0.1
Summary: Modules to read and manipulate many file formats related to Debian packages and repositories
Author-email: Debian python-debian Maintainers <pkg-python-debian-maint@lists.alioth.debian.org>
License: GPL-2.0-or-later
Project-URL: homepage, https://salsa.debian.org/python-debian-team/python-debian
Keywords: debian,linux,metadata,packages,packaging
Platform: any
Classifier: Development Status :: 5 - Production/Stable
Classifier: Programming Language :: Python
Classifier: Intended Audience :: Developers
Classifier: License :: DFSG approved
Classifier: License :: OSI Approved :: GNU General Public License v2 or later (GPLv2+)
Classifier: Operating System :: POSIX
Requires-Python: >=3.7
Provides-Extra: test
